practico/tps/TP5/src/alu.sv
`timescale 1ns/1ps

/**
 * ============================================================================
 * Módulo: alu.sv (Unidad Aritmético Lógica Parametrizada)
 * Técnicas Digitales II - UTN FRC
 * Basado en Harris & Harris (Capítulo 4: HDL & Capítulo 7: Microarquitectura)
 * ============================================================================
 * Entradas:
 *   - a, b: Operandos de N bits
 *   - alu_control: Selector de operación (3 bits)
 *       3'b000: ADD (Suma: a + b)
 *       3'b001: SUB (Resta: a - b)
 *       3'b010: AND (Operación lógica Y: a & b)
 *       3'b011: OR  (Operación lógica O: a | b)
 *       3'b100: XOR (Operación O exclusiva: a ^ b)
 *       3'b101: SLT (Set on Less Than: resultado = 1 si a < b con signo, 0 sino)
 * Salidas:
 *   - result: Resultado de N bits
 *   - zero: Bandera Z (1 si result == 0)
 *   - negative: Bandera N (1 si el bit más significativo de result es 1)
 * ============================================================================
 */

module alu #(
    parameter WIDTH = 8
)(
    input  logic [WIDTH-1:0] a,
    input  logic [WIDTH-1:0] b,
    input  logic [2:0]       alu_control,
    output logic [WIDTH-1:0] result,
    output logic             zero,
    output logic             negative
);

    // Lógica combinacional usando always_comb (SystemVerilog)
    always_comb begin
        case (alu_control)
            3'b000: result = a + b;                                            // ADD
            3'b001: result = a - b;                                            // SUB
            3'b010: result = a & b;                                            // AND
            3'b011: result = a | b;                                            // OR
            3'b100: result = a ^ b;                                            // XOR
            3'b101: result = ($signed(a) < $signed(b)) ? {{(WIDTH-1){1'b0}}, 1'b1} : {WIDTH{1'b0}}; // SLT
            default: result = {WIDTH{1'b0}};
        endcase
    end

    // Generación de Banderas de Estado
    assign zero     = (result == {WIDTH{1'b0}});
    assign negative = result[WIDTH-1];

endmodule

práctico/Tps/TP5/src/alu_tb.sv
`timescale 1ns/1ps

/**
 * ============================================================================
 * Testbench: alu_tb.sv (Banco de pruebas para la ALU)
 * ============================================================================
 */

module alu_tb;

    localparam WIDTH = 8;

    // Señales de estímulo y monitoreo
    logic [WIDTH-1:0] a;
    logic [WIDTH-1:0] b;
    logic [2:0]       alu_control;
    logic [WIDTH-1:0] result;
    logic             zero;
    logic             negative;

    // Instanciación del módulo bajo prueba (DUT)
    alu #(.WIDTH(WIDTH)) dut (
        .a(a),
        .b(b),
        .alu_control(alu_control),
        .result(result),
        .zero(zero),
        .negative(negative)
    );

    // Procedimiento de prueba
    initial begin
        // Configurar volcado de ondas para GTKWave
        $dumpfile("alu.vcd");
        $dumpvars(0, alu_tb);

        $display("=================================================");
        $display("   Iniciando Simulacion de Prueba de ALU (8 bits)");
        $display("=================================================");

        // Test 1: Suma (ADD) -> 15 + 10 = 25
        a = 8'd15; b = 8'd10; alu_control = 3'b000;
        #10;
        $display("[ADD] a=%0d, b=%0d => result=%0d, Z=%b, N=%b (Esperado: 25, Z=0)", a, b, result, zero, negative);

        // Test 2: Resta con resultado cero (SUB) -> 42 - 42 = 0
        a = 8'd42; b = 8'd42; alu_control = 3'b001;
        #10;
        $display("[SUB] a=%0d, b=%0d => result=%0d, Z=%b, N=%b (Esperado: 0, Z=1)", a, b, result, zero, negative);

        // Test 3: Resta con resultado negativo -> 10 - 25 = -15 (241 en uint8)
        a = 8'd10; b = 8'd25; alu_control = 3'b001;
        #10;
        $display("[SUB] a=%0d, b=%0d => result=0x%0h (%0d signed), Z=%b, N=%b (Esperado: N=1)", a, b, result, $signed(result), zero, negative);

        // Test 4: Operacion AND bit a bit -> 0xF0 & 0xAA = 0xA0
        a = 8'hF0; b = 8'hAA; alu_control = 3'b010;
        #10;
        $display("[AND] a=0x%0h, b=0x%0h => result=0x%0h (Esperado: 0xA0)", a, b, result);

        // Test 5: Operacion OR bit a bit -> 0x55 | 0xAA = 0xFF
        a = 8'h55; b = 8'hAA; alu_control = 3'b011;
        #10;
        $display("[OR ] a=0x%0h, b=0x%0h => result=0x%0h (Esperado: 0xFF)", a, b, result);

        // Test 6: Operacion XOR -> 0xFF ^ 0x0F = 0xF0
        a = 8'hFF; b = 8'h0F; alu_control = 3'b100;
        #10;
        $display("[XOR] a=0x%0h, b=0x%0h => result=0x%0h (Esperado: 0xF0)", a, b, result);

        // Test 7: Set on Less Than (SLT) -> -5 < 10 (Verdadero => 1)
        a = -8'sd5; b = 8'sd10; alu_control = 3'b101;
        #10;
        $display("[SLT] a=%0d, b=%0d => result=%0d (Esperado: 1)", $signed(a), $signed(b), result);

        // Test 8: Set on Less Than (SLT) -> 20 < 10 (Falso => 0)
        a = 8'sd20; b = 8'sd10; alu_control = 3'b101;
        #10;
        $display("[SLT] a=%0d, b=%0d => result=%0d (Esperado: 0)", $signed(a), $signed(b), result);

        $display("=================================================");
        $display("   Simulacion completada exitosamente!");
        $display("   Archivo de ondas generado: alu.vcd");
        $display("=================================================");
        $finish;
    end

endmodule

practico/tps/TP5/alu.vcd
$date
	Sun Aug 30 12:58:31 2026
$end
$version
	Icarus Verilog
$end
$timescale
	1ps
$end
$scope module alu_tb $end
$var wire 1 ! zero $end
$var wire 8 " result [7:0] $end
$var wire 1 # negative $end
$var parameter 32 $ WIDTH $end
$var reg 8 % a [7:0] $end
$var reg 3 & alu_control [2:0] $end
$var reg 8 ' b [7:0] $end
$scope module dut $end
$var wire 8 ( a [7:0] $end
$var wire 3 ) alu_control [2:0] $end
$var wire 8 * b [7:0] $end
$var wire 1 ! zero $end
$var wire 1 # negative $end
$var parameter 32 + WIDTH $end
$var reg 8 , result [7:0] $end
$upscope $end
$upscope $end
$enddefinitions $end
$comment Show the parameter values. $end
$dumpall
b1000 +
b1000 $
$end
#0
$dumpvars
b11001 ,
b1010 *
b0 )
b1111 (
b1010 '
b0 &
b1111 %
0#
b11001 "
0!
$end
#10000
1!
b0 "
b0 ,
b1 &
b1 )
b101010 '
b101010 *
b101010 %
b101010 (
#20000
1#
0!
b11110001 "
b11110001 ,
b11001 '
b11001 *
b1010 %
b1010 (
#30000
b10100000 "
b10100000 ,
b10 &
b10 )
b10101010 '
b10101010 *
b11110000 %
b11110000 (
#40000
b11111111 "
b11111111 ,
b11 &
b11 )
b1010101 %
b1010101 (
#50000
b11110000 "
b11110000 ,
b100 &
b100 )
b1111 '
b1111 *
b11111111 %
b11111111 (
#60000
0#
b1 "
b1 ,
b101 &
b101 )
b1010 '
b1010 *
b11111011 %
b11111011 (
#70000
1!
b0 "
b0 ,
b10100 %
b10100 (
